topsis_dhruv_102303877/__init__.py
topsis_dhruv_102303877/topsis.py
topsis_dhruv_102303877-0.0.4.dist-info/METADATA
topsis_dhruv_102303877-0.0.4.dist-info/WHEEL
topsis_dhruv_102303877-0.0.4.dist-info/entry_points.txt
topsis_dhruv_102303877-0.0.4.dist-info/top_level.txt
topsis_dhruv_102303877-0.0.4.dist-info/RECORD
