Metadata-Version: 2.4
Name: TOPSIS-Dhruv-102303877
Version: 0.0.4
Summary: TOPSIS implementation using Python
Author: Dhruv Gupta
Requires-Dist: pandas
Requires-Dist: numpy
Dynamic: author
Dynamic: requires-dist
Dynamic: summary
